exratepy/__init__.py
exratepy/api.py
exratepy/client.py
exratepy/exceptions.py
exratepy/models.py
exratepy/py.typed
exratepy-0.1.0.dist-info/METADATA
exratepy-0.1.0.dist-info/WHEEL
exratepy-0.1.0.dist-info/entry_points.txt
exratepy-0.1.0.dist-info/licenses/LICENSE
exratepy-0.1.0.dist-info/RECORD
