Metadata-Version: 2.4
Name: exratepy
Version: 0.1.0
Summary: Python wrapper for fawazahmed0's exchange-api.
Author-email: Akshay Prabhu <prabhuakshay9@yahoo.com>
License-File: LICENSE
Requires-Python: >=3.12
Requires-Dist: loguru>=0.7.3
Requires-Dist: pydantic>=2.10.6
Requires-Dist: requests>=2.32.3
